MANIFEST.in
README
setup.py
Flask_Silk.egg-info/PKG-INFO
Flask_Silk.egg-info/SOURCES.txt
Flask_Silk.egg-info/dependency_links.txt
Flask_Silk.egg-info/namespace_packages.txt
Flask_Silk.egg-info/not-zip-safe
Flask_Silk.egg-info/requires.txt
Flask_Silk.egg-info/top_level.txt
flaskext/__init__.py
flaskext/silk/__init__.py
flaskext/silk/icons/__init__.py
flaskext/silk/icons/__init__.pyc
flaskext/silk/icons/accept.png
flaskext/silk/icons/add.png
flaskext/silk/icons/anchor.png
flaskext/silk/icons/application.png
flaskext/silk/icons/application_add.png
flaskext/silk/icons/application_cascade.png
flaskext/silk/icons/application_delete.png
flaskext/silk/icons/application_double.png
flaskext/silk/icons/application_edit.png
flaskext/silk/icons/application_error.png
flaskext/silk/icons/application_form.png
flaskext/silk/icons/application_form_add.png
flaskext/silk/icons/application_form_delete.png
flaskext/silk/icons/application_form_edit.png
flaskext/silk/icons/application_form_magnify.png
flaskext/silk/icons/application_get.png
flaskext/silk/icons/application_go.png
flaskext/silk/icons/application_home.png
flaskext/silk/icons/application_key.png
flaskext/silk/icons/application_lightning.png
flaskext/silk/icons/application_link.png
flaskext/silk/icons/application_osx.png
flaskext/silk/icons/application_osx_terminal.png
flaskext/silk/icons/application_put.png
flaskext/silk/icons/application_side_boxes.png
flaskext/silk/icons/application_side_contract.png
flaskext/silk/icons/application_side_expand.png
flaskext/silk/icons/application_side_list.png
flaskext/silk/icons/application_side_tree.png
flaskext/silk/icons/application_split.png
flaskext/silk/icons/application_tile_horizontal.png
flaskext/silk/icons/application_tile_vertical.png
flaskext/silk/icons/application_view_columns.png
flaskext/silk/icons/application_view_detail.png
flaskext/silk/icons/application_view_gallery.png
flaskext/silk/icons/application_view_icons.png
flaskext/silk/icons/application_view_list.png
flaskext/silk/icons/application_view_tile.png
flaskext/silk/icons/application_xp.png
flaskext/silk/icons/application_xp_terminal.png
flaskext/silk/icons/arrow_branch.png
flaskext/silk/icons/arrow_divide.png
flaskext/silk/icons/arrow_down.png
