Metadata-Version: 1.0
Name: Flask-Silk
Version: 0.1.1
Summary: Adds silk icons to your Flask application or module, or extension.
Home-page: http://github.com/sublee/flask-silk
Author: Lee Heung-sub
Author-email: heung@sublee.kr
License: BSD
Platform: any
Classifier: Development Status :: 4 - Beta
Classifier: Environment :: Web Environment
Classifier: Intended Audience :: Developers
Classifier: License :: OSI Approved :: BSD License
Classifier: Operating System :: OS Independent
Classifier: Programming Language :: Python
Classifier: Topic :: Internet :: WWW/HTTP :: Dynamic Content
Classifier: Topic :: Software Development :: Libraries :: Python Modules
